chromaformatter/__init__.py
chromaformatter/py.typed
chromaformatter-6.0.0.dist-info/LICENSE
chromaformatter-6.0.0.dist-info/WHEEL
chromaformatter-6.0.0.dist-info/METADATA
chromaformatter-6.0.0.dist-info/RECORD
