Metadata-Version: 2.1
Name: chromaformatter
Version: 6.0.0
Summary: Wrapper for the Python logging formatter that adds color.
Home-page: https://gitlab.com/mburkard/chroma-formatter
License: MIT
Author: Matthew Burkard
Author-email: matthewjburkard@gmail.com
Requires-Python: >=3.8,<4.0
Classifier: License :: OSI Approved :: MIT License
Classifier: Programming Language :: Python :: 3
Classifier: Programming Language :: Python :: 3.10
Classifier: Programming Language :: Python :: 3.8
Classifier: Programming Language :: Python :: 3.9
Requires-Dist: colorama (>=0.4.4,<0.5.0)
Project-URL: Repository, https://gitlab.com/mburkard/chroma-formatter
